chat_completions_conversation.py
chat_completions_conversation-0.1.0a1.dist-info/licenses/LICENSE
chat_completions_conversation-0.1.0a1.dist-info/METADATA
chat_completions_conversation-0.1.0a1.dist-info/WHEEL
chat_completions_conversation-0.1.0a1.dist-info/top_level.txt
chat_completions_conversation-0.1.0a1.dist-info/RECORD
