Metadata-Version: 2.4
Name: chat-completions-conversation
Version: 0.1.0a1
Summary: A Python 2+ library for conversations with LLMs providing an OpenAI Chat Completions-compatible API. That includes OpenAI's models, Google Gemini, DeepSeek, and anything you can run on ollama.
Author-email: Jifeng Wu <jifengwu2k@gmail.com>
License-Expression: MIT
Project-URL: Homepage, https://github.com/jifengwu2k/chat-completions-conversation
Project-URL: Bug Tracker, https://github.com/jifengwu2k/chat-completions-conversation/issues
Classifier: Programming Language :: Python :: 2
Classifier: Programming Language :: Python :: 3
Classifier: Operating System :: OS Independent
Requires-Python: >=2
License-File: LICENSE
Requires-Dist: enum34; python_version < "3.4"
Requires-Dist: intersperse
Requires-Dist: textcompat
Requires-Dist: typing; python_version < "3.5"
Dynamic: license-file
